./.gitignore
./LICENSE
./PKG-INFO
./PUBLISHING.md
./README.md
./TEST_RESULTS.md
./pyproject.toml
./server.py
./Support/Claude/claude_desktop_config.json
utforska_data_mcp-1.0.1.dist-info/METADATA
utforska_data_mcp-1.0.1.dist-info/WHEEL
utforska_data_mcp-1.0.1.dist-info/entry_points.txt
utforska_data_mcp-1.0.1.dist-info/licenses/LICENSE
utforska_data_mcp-1.0.1.dist-info/RECORD
