Metadata-Version: 2.4
Name: utforska-data-mcp
Version: 1.0.1
Summary: MCP server for Swedish statistical data discovery and export
Project-URL: Homepage, https://utforskadata.se
Project-URL: Repository, https://github.com/deslay1/data-platform
Author-email: Utforska Data <datary@protonmail.com>
License: MIT
License-File: LICENSE
Keywords: ai,data,mcp,scb,statistics,sweden
Classifier: Development Status :: 4 - Beta
Classifier: Intended Audience :: Developers
Classifier: License :: OSI Approved :: MIT License
Classifier: Programming Language :: Python :: 3
Classifier: Programming Language :: Python :: 3.10
Classifier: Programming Language :: Python :: 3.11
Classifier: Programming Language :: Python :: 3.12
Requires-Python: >=3.10
Requires-Dist: httpx>=0.25.0
Requires-Dist: mcp>=1.0.0
